gitly/__init__.py
gitly/colab/__init__.py
gitly/colab/plot.py
gitly-1.1.1.dist-info/LICENSE
gitly-1.1.1.dist-info/METADATA
gitly-1.1.1.dist-info/WHEEL
gitly-1.1.1.dist-info/top_level.txt
gitly-1.1.1.dist-info/RECORD
