Metadata-Version: 2.1
Name: gitly
Version: 1.1.1
Summary: This is a lib to help you plot your fency graphs from plotly in github while using Google Colab notebook.
Home-page: https://github.com/Tiagoeem/gitly
Author: Tiago Sanches da Silva
Author-email: tiago.eem@gmail.com
License: mit
Platform: UNKNOWN
Classifier: Programming Language :: Python :: 3
Classifier: License :: OSI Approved :: MIT License
Classifier: Operating System :: OS Independent
Requires-Dist: plotly (>=4.9.0)
Requires-Dist: kaleido
